setup.py
slack/__init__.py
slack/cli.py
slack_webhook_cli.egg-info/PKG-INFO
slack_webhook_cli.egg-info/SOURCES.txt
slack_webhook_cli.egg-info/dependency_links.txt
slack_webhook_cli.egg-info/entry_points.txt
slack_webhook_cli.egg-info/requires.txt
slack_webhook_cli.egg-info/top_level.txt