Metadata-Version: 1.0
Name: slack-webhook-cli
Version: 0.2.4
Summary: Send messages to Slack from the command line
Home-page: https://github.com/philippbosch/slack-webhook-cli
Author: Philipp Bosch
Author-email: hello@pb.io
License: MIT
Platform: UNKNOWN
